setup.py
dsnd_probability_io_01/Binomialdistribution.py
dsnd_probability_io_01/Gaussiandistribution.py
dsnd_probability_io_01/Generaldistribution.py
dsnd_probability_io_01/__init__.py
dsnd_probability_io_01.egg-info/PKG-INFO
dsnd_probability_io_01.egg-info/SOURCES.txt
dsnd_probability_io_01.egg-info/dependency_links.txt
dsnd_probability_io_01.egg-info/not-zip-safe
dsnd_probability_io_01.egg-info/top_level.txt