Metadata-Version: 1.0
Name: dsnd-probability-io-01
Version: 1.1
Summary: Gaussian and Binomial distributions
Home-page: UNKNOWN
Author: Ishmael Obeso
Author-email: gobestupidsomewhereelse@gmail.com
License: UNKNOWN
Platform: UNKNOWN
